paybybot/__init__.py
paybybot/bot.py
paybybot/config.py
paybybot/notifs.py
paybybot/test.py
paybybot/ui.py
paybybot-0.0.4.dist-info/METADATA
paybybot-0.0.4.dist-info/RECORD
paybybot-0.0.4.dist-info/WHEEL
paybybot-0.0.4.dist-info/entry_points.txt
paybybot-0.0.4.dist-info/top_level.txt
