Metadata-Version: 2.1
Name: paybybot
Version: 0.0.4
Summary: Notifications for https://www.paybyphone.fr/
Home-page: https://github.com/louisabraham/paybybot
Author: Louis Abraham
Author-email: louis.abraham@yahoo.fr
License: MIT
Platform: UNKNOWN
Classifier: Topic :: Utilities
Requires-Python: >=3.5
Requires-Dist: selenium
Requires-Dist: dateparser
Requires-Dist: pyyaml
Requires-Dist: schedule
